pylibcontroller/__init__.py
pylibcontroller/controller.py
pylibcontroller/error_handler.py
pylibcontroller/__pycache__/__init__.cpython-313.pyc
pylibcontroller/__pycache__/controller.cpython-313.pyc
pylibcontroller/__pycache__/error_handler.cpython-313.pyc
pylibcontroller/utils/__init__.py
pylibcontroller/utils/package_manager.py
pylibcontroller/utils/__pycache__/__init__.cpython-313.pyc
pylibcontroller/utils/__pycache__/package_manager.cpython-313.pyc
pylibcontroller-0.1.0.dist-info/licenses/LICENSE
pylibcontroller-0.1.0.dist-info/METADATA
pylibcontroller-0.1.0.dist-info/WHEEL
pylibcontroller-0.1.0.dist-info/top_level.txt
pylibcontroller-0.1.0.dist-info/RECORD
