Metadata-Version: 2.4
Name: pylibcontroller
Version: 0.1.0
Summary: A Python library manager that automatically installs missing libraries
Home-page: https://github.com/yourusername/pylibcontroller
Author: Berat O**ani
License: MIT License
Keywords: library,manager,auto-install,dependency
Classifier: Programming Language :: Python :: 3
Classifier: License :: OSI Approved :: MIT License
Classifier: Operating System :: OS Independent
Requires-Python: >=3.6
License-File: LICENSE
Dynamic: home-page
Dynamic: license-file
Dynamic: requires-python
